Metadata-Version: 1.0
Name: ceph-installer
Version: 1.3.0
Summary: An HTTP API that provides Ceph installation/configuration endpoints
Home-page: UNKNOWN
Author: UNKNOWN
Author-email: UNKNOWN
License: UNKNOWN
Platform: UNKNOWN
